{
    "ukprn": "10007769",
    "name": "London Business School",
    "latitude": 51.526583,
    "longitude": -0.161353,
    "years": [
        {
            "year": "2018/19",
            "total_count": 490,
            "regions": [
                {
                    "domicile_region": "North East",
                    "total_count": 0,
                    "count_percentage": 0.0
                },
                {
                    "domicile_region": "North West",
                    "total_count": 5,
                    "count_percentage": 1.0204081632653061
                },
                {
                    "domicile_region": "Yorkshire and The Humber",
                    "total_count": 0,
                    "count_percentage": 0.0
                },
                {
                    "domicile_region": "East Midlands",
                    "total_count": 35,
                    "count_percentage": 7.142857142857142
                },
                {
                    "domicile_region": "West Midlands",
                    "total_count": 10,
                    "count_percentage": 2.0408163265306123
                },
                {
                    "domicile_region": "Eastern",
                    "total_count": 15,
                    "count_percentage": 3.061224489795918
                },
                {
                    "domicile_region": "London",
                    "total_count": 385,
                    "count_percentage": 78.57142857142857
                },
                {
                    "domicile_region": "South East",
                    "total_count": 35,
                    "count_percentage": 7.142857142857142
                },
                {
                    "domicile_region": "South West",
                    "total_count": 0,
                    "count_percentage": 0.0
                },
                {
                    "domicile_region": "Northern Ireland",
                    "total_count": 0,
                    "count_percentage": 0.0
                },
                {
                    "domicile_region": "Scotland",
                    "total_count": 5,
                    "count_percentage": 1.0204081632653061
                },
                {
                    "domicile_region": "Wales",
                    "total_count": 0,
                    "count_percentage": 0.0
                }
            ]
        },
        {
            "year": "2016/17",
            "total_count": 545,
            "regions": [
                {
                    "domicile_region": "North East",
                    "total_count": 0,
                    "count_percentage": 0.0
                },
                {
                    "domicile_region": "North West",
                    "total_count": 5,
                    "count_percentage": 0.9174311926605505
                },
                {
                    "domicile_region": "Yorkshire and The Humber",
                    "total_count": 0,
                    "count_percentage": 0.0
                },
                {
                    "domicile_region": "East Midlands",
                    "total_count": 35,
                    "count_percentage": 6.422018348623854
                },
                {
                    "domicile_region": "West Midlands",
                    "total_count": 10,
                    "count_percentage": 1.834862385321101
                },
                {
                    "domicile_region": "Eastern",
                    "total_count": 10,
                    "count_percentage": 1.834862385321101
                },
                {
                    "domicile_region": "London",
                    "total_count": 445,
                    "count_percentage": 81.65137614678899
                },
                {
                    "domicile_region": "South East",
                    "total_count": 40,
                    "count_percentage": 7.339449541284404
                },
                {
                    "domicile_region": "South West",
                    "total_count": 0,
                    "count_percentage": 0.0
                },
                {
                    "domicile_region": "Northern Ireland",
                    "total_count": 0,
                    "count_percentage": 0.0
                },
                {
                    "domicile_region": "Scotland",
                    "total_count": 0,
                    "count_percentage": 0.0
                },
                {
                    "domicile_region": "Wales",
                    "total_count": 0,
                    "count_percentage": 0.0
                }
            ]
        },
        {
            "year": "2015/16",
            "total_count": 580,
            "regions": [
                {
                    "domicile_region": "North East",
                    "total_count": 0,
                    "count_percentage": 0.0
                },
                {
                    "domicile_region": "North West",
                    "total_count": 0,
                    "count_percentage": 0.0
                },
                {
                    "domicile_region": "Yorkshire and The Humber",
                    "total_count": 0,
                    "count_percentage": 0.0
                },
                {
                    "domicile_region": "East Midlands",
                    "total_count": 65,
                    "count_percentage": 11.206896551724139
                },
                {
                    "domicile_region": "West Midlands",
                    "total_count": 5,
                    "count_percentage": 0.8620689655172413
                },
                {
                    "domicile_region": "Eastern",
                    "total_count": 15,
                    "count_percentage": 2.586206896551724
                },
                {
                    "domicile_region": "London",
                    "total_count": 465,
                    "count_percentage": 80.17241379310344
                },
                {
                    "domicile_region": "South East",
                    "total_count": 25,
                    "count_percentage": 4.310344827586207
                },
                {
                    "domicile_region": "South West",
                    "total_count": 5,
                    "count_percentage": 0.8620689655172413
                },
                {
                    "domicile_region": "Northern Ireland",
                    "total_count": 0,
                    "count_percentage": 0.0
                },
                {
                    "domicile_region": "Scotland",
                    "total_count": 0,
                    "count_percentage": 0.0
                },
                {
                    "domicile_region": "Wales",
                    "total_count": 0,
                    "count_percentage": 0.0
                }
            ]
        },
        {
            "year": "2019/20",
            "total_count": 450,
            "regions": [
                {
                    "domicile_region": "North East",
                    "total_count": 0,
                    "count_percentage": 0.0
                },
                {
                    "domicile_region": "North West",
                    "total_count": 0,
                    "count_percentage": 0.0
                },
                {
                    "domicile_region": "Yorkshire and The Humber",
                    "total_count": 0,
                    "count_percentage": 0.0
                },
                {
                    "domicile_region": "East Midlands",
                    "total_count": 60,
                    "count_percentage": 13.333333333333334
                },
                {
                    "domicile_region": "West Midlands",
                    "total_count": 5,
                    "count_percentage": 1.1111111111111112
                },
                {
                    "domicile_region": "Eastern",
                    "total_count": 10,
                    "count_percentage": 2.2222222222222223
                },
                {
                    "domicile_region": "London",
                    "total_count": 350,
                    "count_percentage": 77.77777777777779
                },
                {
                    "domicile_region": "South East",
                    "total_count": 25,
                    "count_percentage": 5.555555555555555
                },
                {
                    "domicile_region": "South West",
                    "total_count": 0,
                    "count_percentage": 0.0
                },
                {
                    "domicile_region": "Northern Ireland",
                    "total_count": 0,
                    "count_percentage": 0.0
                },
                {
                    "domicile_region": "Scotland",
                    "total_count": 0,
                    "count_percentage": 0.0
                },
                {
                    "domicile_region": "Wales",
                    "total_count": 0,
                    "count_percentage": 0.0
                }
            ]
        },
        {
            "year": "2014/15",
            "total_count": 515,
            "regions": [
                {
                    "domicile_region": "North East",
                    "total_count": 0,
                    "count_percentage": 0.0
                },
                {
                    "domicile_region": "North West",
                    "total_count": 0,
                    "count_percentage": 0.0
                },
                {
                    "domicile_region": "Yorkshire and The Humber",
                    "total_count": 0,
                    "count_percentage": 0.0
                },
                {
                    "domicile_region": "East Midlands",
                    "total_count": 60,
                    "count_percentage": 11.650485436893204
                },
                {
                    "domicile_region": "West Midlands",
                    "total_count": 5,
                    "count_percentage": 0.9708737864077669
                },
                {
                    "domicile_region": "Eastern",
                    "total_count": 15,
                    "count_percentage": 2.912621359223301
                },
                {
                    "domicile_region": "London",
                    "total_count": 405,
                    "count_percentage": 78.64077669902912
                },
                {
                    "domicile_region": "South East",
                    "total_count": 30,
                    "count_percentage": 5.825242718446602
                },
                {
                    "domicile_region": "South West",
                    "total_count": 0,
                    "count_percentage": 0.0
                },
                {
                    "domicile_region": "Northern Ireland",
                    "total_count": 0,
                    "count_percentage": 0.0
                },
                {
                    "domicile_region": "Scotland",
                    "total_count": 0,
                    "count_percentage": 0.0
                },
                {
                    "domicile_region": "Wales",
                    "total_count": 0,
                    "count_percentage": 0.0
                }
            ]
        },
        {
            "year": "2020/21",
            "total_count": 470,
            "regions": [
                {
                    "domicile_region": "North East",
                    "total_count": 0,
                    "count_percentage": 0.0
                },
                {
                    "domicile_region": "North West",
                    "total_count": 5,
                    "count_percentage": 1.0638297872340425
                },
                {
                    "domicile_region": "Yorkshire and The Humber",
                    "total_count": 5,
                    "count_percentage": 1.0638297872340425
                },
                {
                    "domicile_region": "East Midlands",
                    "total_count": 5,
                    "count_percentage": 1.0638297872340425
                },
                {
                    "domicile_region": "West Midlands",
                    "total_count": 5,
                    "count_percentage": 1.0638297872340425
                },
                {
                    "domicile_region": "Eastern",
                    "total_count": 15,
                    "count_percentage": 3.1914893617021276
                },
                {
                    "domicile_region": "London",
                    "total_count": 400,
                    "count_percentage": 85.1063829787234
                },
                {
                    "domicile_region": "South East",
                    "total_count": 35,
                    "count_percentage": 7.446808510638298
                },
                {
                    "domicile_region": "South West",
                    "total_count": 0,
                    "count_percentage": 0.0
                },
                {
                    "domicile_region": "Northern Ireland",
                    "total_count": 0,
                    "count_percentage": 0.0
                },
                {
                    "domicile_region": "Scotland",
                    "total_count": 0,
                    "count_percentage": 0.0
                },
                {
                    "domicile_region": "Wales",
                    "total_count": 0,
                    "count_percentage": 0.0
                }
            ]
        },
        {
            "year": "2017/18",
            "total_count": 520,
            "regions": [
                {
                    "domicile_region": "North East",
                    "total_count": 0,
                    "count_percentage": 0.0
                },
                {
                    "domicile_region": "North West",
                    "total_count": 10,
                    "count_percentage": 1.9230769230769231
                },
                {
                    "domicile_region": "Yorkshire and The Humber",
                    "total_count": 0,
                    "count_percentage": 0.0
                },
                {
                    "domicile_region": "East Midlands",
                    "total_count": 5,
                    "count_percentage": 0.9615384615384616
                },
                {
                    "domicile_region": "West Midlands",
                    "total_count": 5,
                    "count_percentage": 0.9615384615384616
                },
                {
                    "domicile_region": "Eastern",
                    "total_count": 15,
                    "count_percentage": 2.8846153846153846
                },
                {
                    "domicile_region": "London",
                    "total_count": 435,
                    "count_percentage": 83.65384615384616
                },
                {
                    "domicile_region": "South East",
                    "total_count": 35,
                    "count_percentage": 6.730769230769231
                },
                {
                    "domicile_region": "South West",
                    "total_count": 0,
                    "count_percentage": 0.0
                },
                {
                    "domicile_region": "Northern Ireland",
                    "total_count": 0,
                    "count_percentage": 0.0
                },
                {
                    "domicile_region": "Scotland",
                    "total_count": 15,
                    "count_percentage": 2.8846153846153846
                },
                {
                    "domicile_region": "Wales",
                    "total_count": 0,
                    "count_percentage": 0.0
                }
            ]
        }
    ]
}